vgate/__init__.py
vgate/communicator.py
vgate/cue_baser.py
vgate/httping.py
vgate/presentation_proof_handler.py
vgate/protocoling.py
vgate/py.typed
vgate-0.1.4.dist-info/METADATA
vgate-0.1.4.dist-info/WHEEL
vgate-0.1.4.dist-info/RECORD
