Metadata-Version: 2.4
Name: vgate
Version: 0.1.4
Summary: ACDC Presentation Handler library
Project-URL: Homepage, https://github.com/kentbull/vgate
Project-URL: Repository, https://github.com/kentbull/vgate
Project-URL: Documentation, https://github.com/kentbull/vgate#readme
Project-URL: Issues, https://github.com/kentbull/vgate/issues
Author-email: Kevin Griffin <kevin.griffin@gleif.org>
License: Apache-2.0
Keywords: acdc,credential,keri,presentation,vlei
Classifier: Development Status :: 4 - Beta
Classifier: Intended Audience :: Developers
Classifier: License :: OSI Approved :: Apache Software License
Classifier: Programming Language :: Python :: 3
Classifier: Programming Language :: Python :: 3.12
Classifier: Topic :: Security
Classifier: Topic :: Software Development :: Libraries :: Python Modules
Requires-Python: >=3.12.6
Requires-Dist: falcon>=3.1.3
Requires-Dist: hio<0.6.19,>=0.6.14
Requires-Dist: http-sfv>=0.9.9
Requires-Dist: keri<1.3.0,>=1.2.7
